{
	"id": "795b61f2-ace8-42b0-bf97-4b1faed62c08",
	"name": "localhost",
	"values": [
		{
			"key": "url",
			"value": "https://localhost:5001",
			"description": {
				"content": "",
				"type": "text/plain"
			},
			"enabled": true
		},
		{
			"key": "token",
			"value": "",
			"description": {
				"content": "",
				"type": "text/plain"
			},
			"enabled": true
		},
		{
			"key": "userid",
			"value": "",
			"description": {
				"content": "",
				"type": "text/plain"
			},
			"enabled": true
		},
		{
			"key": "avatarid",
			"value": "",
			"description": {
				"content": "",
				"type": "text/plain"
			},
			"enabled": true
		},
		{
			"key": "scriptid",
			"value": "",
			"description": {
				"content": "",
				"type": "text/plain"
			},
			"enabled": true
		}
	],
	"_postman_variable_scope": "environment",
	"_postman_exported_at": "2019-01-31T23:56:29.442Z",
	"_postman_exported_using": "Postman/6.7.2"
}